loudstream/__init__.py
loudstream/_ffi.py
loudstream/meter.py
loudstream/normalize.py
loudstream/source.py
loudstream-0.2.3.dist-info/METADATA
loudstream-0.2.3.dist-info/WHEEL
loudstream-0.2.3.dist-info/top_level.txt
loudstream-0.2.3.dist-info/RECORD
